myfunctions_edatop/__init__.py
myfunctions_edatop/math.py
myfunctions_edatop-0.0.10.dist-info/METADATA
myfunctions_edatop-0.0.10.dist-info/WHEEL
myfunctions_edatop-0.0.10.dist-info/top_level.txt
myfunctions_edatop-0.0.10.dist-info/RECORD
